dash_auth/__init__.py
dash_auth/api_client.py
dash_auth/configuration.py
dash_auth/rest.py
dash_auth/api/__init__.py
dash_auth/api/account_api.py
dash_auth/api/login_api.py
dash_auth/api/logout_api.py
dash_auth/api/password_api.py
dash_auth/models/__init__.py
dash_auth/models/authentication_scheme.py
dash_auth/models/change_password_request.py
dash_auth/models/logout.py
dash_auth/models/register.py
dash_auth/models/user.py
dash_auth/models/user_address.py
dash_auth/models/user_login.py
dash_auth/models/user_query.py
dash_auth_python_client-0.1.1.dist-info/METADATA
dash_auth_python_client-0.1.1.dist-info/RECORD
dash_auth_python_client-0.1.1.dist-info/WHEEL
dash_auth_python_client-0.1.1.dist-info/top_level.txt
test/__init__.py
test/test_account_api.py
test/test_authentication_scheme.py
test/test_change_password_request.py
test/test_login_api.py
test/test_logout.py
test/test_logout_api.py
test/test_password_api.py
test/test_register.py
test/test_user.py
test/test_user_address.py
test/test_user_login.py
test/test_user_query.py
